<fonts>
    <fontCodePoint>
        <code>5492</code>
    </fontCodePoint>
    <fontCodePoint>
        <code>5710</code>
    </fontCodePoint>
    <fontCodePoint>
        <code>5709</code>
    </fontCodePoint>
    <fontCodePoint>
        <code>5511</code>
    </fontCodePoint>
    <fontCodePoint>
        <code>5558</code>
    </fontCodePoint>
    <fontCodePoint>
        <code>5563</code>
    </fontCodePoint>
    <fontCodePoint>
        <code>5207</code>
    </fontCodePoint>
    <fontCodePoint>
        <code>5375</code>
    </fontCodePoint>
    <fontCodePoint>
        <code>5326</code>
    </fontCodePoint>
    <fontCodePoint>
        <code>5503</code>
    </fontCodePoint>
    <fontCodePoint>
        <code>5573</code>
    </fontCodePoint>
    <fontCodePoint>
        <code>83</code>
    </fontCodePoint>
    <fontCodePoint>
        <code>5611</code>
    </fontCodePoint>
    <fontCodePoint>
        <code>5556</code>
    </fontCodePoint>
    <fontCodePoint>
        <code>5660</code>
    </fontCodePoint>
    <fontCodePoint>
        <code>5500</code>
    </fontCodePoint>
    <fontCodePoint>
        <code>5273</code>
    </fontCodePoint>
    <fontCodePoint>
        <code>5565 5176</code>
    </fontCodePoint>
    <fontCodePoint>
        <code>5290</code>
    </fontCodePoint>
    <fontCodePoint>
        <code>5731</code>
    </fontCodePoint>
    <fontCodePoint>
        <code>5741</code>
    </fontCodePoint>
    <fontCodePoint>
        <code>5220</code>
    </fontCodePoint>
    <fontCodePoint>
        <code>5179</code>
    </fontCodePoint>
    <fontCodePoint>
        <code>5720</code>
    </fontCodePoint>
    <fontCodePoint>
        <code>5641</code>
    </fontCodePoint>
    <fontCodePoint>
        <code>5730</code>
    </fontCodePoint>
</fonts>
